perform_topsis/102283009.py
perform_topsis/__init__.py
Topsis_Ananya_102283009-1.0.0.dist-info/LICENSE
Topsis_Ananya_102283009-1.0.0.dist-info/METADATA
Topsis_Ananya_102283009-1.0.0.dist-info/WHEEL
Topsis_Ananya_102283009-1.0.0.dist-info/entry_points.txt
Topsis_Ananya_102283009-1.0.0.dist-info/top_level.txt
Topsis_Ananya_102283009-1.0.0.dist-info/RECORD
