Metadata-Version: 2.1
Name: Topsis-Ananya-102283009
Version: 1.0.0
Summary: Performs TOPSIS
Home-page: https://github.com/ananya-184/102283009
Author: Ananya Gupta
Author-email: ananyagupta184@gmail.com
License: MIT
Classifier: License :: OSI Approved :: MIT License
Classifier: Programming Language :: Python :: 3.6
Classifier: Programming Language :: Python :: 3.7
Classifier: Programming Language :: Python :: 3.8
License-File: LICENSE
